peodd/__init__.py
peodd/_version.py
peodd/peodd.py
peodd-0.4.0.dist-info/entry_points.txt
peodd-0.4.0.dist-info/LICENSE
peodd-0.4.0.dist-info/WHEEL
peodd-0.4.0.dist-info/METADATA
peodd-0.4.0.dist-info/RECORD
